<?xml version="1.0" encoding="UTF-8"?>
<tv>
  <channel id="159">
    <display-name>Italy Serie A : Torino vs Udinese</display-name>
  </channel>
  <programme start="20250423000000 +0000" stop="20250423163000 +0000" channel="159">
    <title lang="it">inizierà alle 18:30.</title>
    <desc lang="it">Italy Serie A : Torino vs Udinese.</desc>
    <category lang="it">Annuncio</category>
  </programme>
  <programme start="20250423163000 +0000" stop="20250423183000 +0000" channel="159">
    <title lang="it">Italy Serie A : Torino vs Udinese</title>
    <desc lang="it">Italy Serie A : Torino vs Udinese trasmesso in diretta.</desc>
    <category lang="it">Soccer</category>
  </programme>
  <channel id="156">
    <display-name>Italy Serie A : Torino vs Udinese</display-name>
  </channel>
  <programme start="20250423000000 +0000" stop="20250423163000 +0000" channel="156">
    <title lang="it">inizierà alle 18:30.</title>
    <desc lang="it">Italy Serie A : Torino vs Udinese.</desc>
    <category lang="it">Annuncio</category>
  </programme>
  <programme start="20250423163000 +0000" stop="20250423183000 +0000" channel="156">
    <title lang="it">Italy Serie A : Torino vs Udinese</title>
    <desc lang="it">Italy Serie A : Torino vs Udinese trasmesso in diretta.</desc>
    <category lang="it">Soccer</category>
  </programme>
  <channel id="870">
    <display-name>Italy Serie A : Torino vs Udinese</display-name>
  </channel>
  <programme start="20250423000000 +0000" stop="20250423163000 +0000" channel="870">
    <title lang="it">inizierà alle 18:30.</title>
    <desc lang="it">Italy Serie A : Torino vs Udinese.</desc>
    <category lang="it">Annuncio</category>
  </programme>
  <programme start="20250423163000 +0000" stop="20250423183000 +0000" channel="870">
    <title lang="it">Italy Serie A : Torino vs Udinese</title>
    <desc lang="it">Italy Serie A : Torino vs Udinese trasmesso in diretta.</desc>
    <category lang="it">Soccer</category>
  </programme>
  <channel id="160">
    <display-name>Italy Serie A : Cagliari vs Fiorentina</display-name>
  </channel>
  <programme start="20250423000000 +0000" stop="20250423163000 +0000" channel="160">
    <title lang="it">inizierà alle 18:30.</title>
    <desc lang="it">Italy Serie A : Cagliari vs Fiorentina.</desc>
    <category lang="it">Annuncio</category>
  </programme>
  <programme start="20250423163000 +0000" stop="20250423183000 +0000" channel="160">
    <title lang="it">Italy Serie A : Cagliari vs Fiorentina</title>
    <desc lang="it">Italy Serie A : Cagliari vs Fiorentina trasmesso in diretta.</desc>
    <category lang="it">Soccer</category>
  </programme>
  <channel id="161">
    <display-name>Italy Serie A : Genoa vs Lazio</display-name>
  </channel>
  <programme start="20250423000000 +0000" stop="20250423163000 +0000" channel="161">
    <title lang="it">inizierà alle 18:30.</title>
    <desc lang="it">Italy Serie A : Genoa vs Lazio.</desc>
    <category lang="it">Annuncio</category>
  </programme>
  <programme start="20250423163000 +0000" stop="20250423183000 +0000" channel="161">
    <title lang="it">Italy Serie A : Genoa vs Lazio</title>
    <desc lang="it">Italy Serie A : Genoa vs Lazio trasmesso in diretta.</desc>
    <category lang="it">Soccer</category>
  </programme>
  <channel id="162">
    <display-name>Italy Serie A : Parma vs Juventus</display-name>
  </channel>
  <programme start="20250423000000 +0000" stop="20250423163000 +0000" channel="162">
    <title lang="it">inizierà alle 18:30.</title>
    <desc lang="it">Italy Serie A : Parma vs Juventus.</desc>
    <category lang="it">Annuncio</category>
  </programme>
  <programme start="20250423163000 +0000" stop="20250423183000 +0000" channel="162">
    <title lang="it">Italy Serie A : Parma vs Juventus</title>
    <desc lang="it">Italy Serie A : Parma vs Juventus trasmesso in diretta.</desc>
    <category lang="it">Soccer</category>
  </programme>
  <channel id="877">
    <display-name>Spain- La Liga : Athletic Club vs Las Palmas</display-name>
  </channel>
  <programme start="20250423000000 +0000" stop="20250423170000 +0000" channel="877">
    <title lang="it">inizierà alle 19:00.</title>
    <desc lang="it">Spain- La Liga : Athletic Club vs Las Palmas.</desc>
    <category lang="it">Annuncio</category>
  </programme>
  <programme start="20250423170000 +0000" stop="20250423190000 +0000" channel="877">
    <title lang="it">Spain- La Liga : Athletic Club vs Las Palmas</title>
    <desc lang="it">Spain- La Liga : Athletic Club vs Las Palmas trasmesso in diretta.</desc>
    <category lang="it">Soccer</category>
  </programme>
  <programme start="20250423000000 +0000" stop="20250423190000 +0000" channel="870">
    <title lang="it">inizierà alle 21:00.</title>
    <desc lang="it">England - Premier League : Arsenal vs Crystal Palace.</desc>
    <category lang="it">Annuncio</category>
  </programme>
  <programme start="20250423190000 +0000" stop="20250423210000 +0000" channel="870">
    <title lang="it">England - Premier League : Arsenal vs Crystal Palace</title>
    <desc lang="it">England - Premier League : Arsenal vs Crystal Palace trasmesso in diretta.</desc>
    <category lang="it">Soccer</category>
  </programme>
  <channel id="3">
    <display-name>Coppa Italia : Internazionale vs Milan</display-name>
  </channel>
  <programme start="20250423000000 +0000" stop="20250423190000 +0000" channel="3">
    <title lang="it">inizierà alle 21:00.</title>
    <desc lang="it">Coppa Italia : Internazionale vs Milan.</desc>
    <category lang="it">Annuncio</category>
  </programme>
  <programme start="20250423190000 +0000" stop="20250423210000 +0000" channel="3">
    <title lang="it">Coppa Italia : Internazionale vs Milan</title>
    <desc lang="it">Coppa Italia : Internazionale vs Milan trasmesso in diretta.</desc>
    <category lang="it">Soccer</category>
  </programme>
  <programme start="20250423000000 +0000" stop="20250423193000 +0000" channel="877">
    <title lang="it">inizierà alle 21:30.</title>
    <desc lang="it">Spain- La Liga : Getafe vs Real Madrid.</desc>
    <category lang="it">Annuncio</category>
  </programme>
  <programme start="20250423193000 +0000" stop="20250423213000 +0000" channel="877">
    <title lang="it">Spain- La Liga : Getafe vs Real Madrid</title>
    <desc lang="it">Spain- La Liga : Getafe vs Real Madrid trasmesso in diretta.</desc>
    <category lang="it">Soccer</category>
  </programme>
</tv>
